image_vision/__init__.py
image_vision/cli.py
image_vision/image_vision.py
image_vision-0.1.0.dist-info/METADATA
image_vision-0.1.0.dist-info/RECORD
image_vision-0.1.0.dist-info/WHEEL
image_vision-0.1.0.dist-info/entry_points.txt
image_vision-0.1.0.dist-info/top_level.txt
