Metadata-Version: 2.1
Name: image-vision
Version: 0.1.0
Summary: Python image_vision provides easy to use functionalities for performing image processing
Home-page: https://github.com/nishgaba-ai/image_vision
Author: Nishchal Gaba
Author-email: nishgaba.ai@gmail.com
License: MIT license
Keywords: image_vision
Platform: UNKNOWN
Classifier: Development Status :: 2 - Pre-Alpha
Classifier: Intended Audience :: Developers
Classifier: License :: OSI Approved :: MIT License
Classifier: Natural Language :: English
Classifier: Programming Language :: Python :: 2
Classifier: Programming Language :: Python :: 2.7
Classifier: Programming Language :: Python :: 3
Classifier: Programming Language :: Python :: 3.4
Classifier: Programming Language :: Python :: 3.5
Classifier: Programming Language :: Python :: 3.6
Requires-Dist: Click (>=6.0)
Requires-Dist: numpy
Requires-Dist: pillow
